MANIFEST.in
cmemcached.py
cmemcached_imp.pyx
setup.cfg
setup.py
split_mc.c
split_mc.h
python_libmemcached.egg-info/PKG-INFO
python_libmemcached.egg-info/SOURCES.txt
python_libmemcached.egg-info/dependency_links.txt
python_libmemcached.egg-info/top_level.txt