Metadata-Version: 1.1
Name: python-libmemcached
Version: 0.40dev
Summary: python memcached client wrapped on libmemcached
Home-page: UNKNOWN
Author: davies
Author-email: davies.liu@gmail.com
License: UNKNOWN
Platform: UNKNOWN
Requires: pyrex
